{
  "accessory": {
    "airpods": 1,
    "bandage": 9,
    "bandana": 8,
    "batman mask": 1,
    "bead": 1,
    "bellboy hat": 1,
    "beret": 6,
    "big beard": 9,
    "big shades": 42,
    "black eyeshadow": 1,
    "blood": 43,
    "bloody eyeshadow": 12,
    "blue eyeshadow": 2,
    "bolero hat": 1,
    "braid beard": 1,
    "bruise": 6,
    "bucket hat": 2,
    "cap": 6,
    "chinstrap": 4,
    "choker": 6,
    "chopstick": 1,
    "cigar": 12,
    "cigarette": 48,
    "classic shades": 31,
    "clown eyeshadow": 1,
    "clown mask": 1,
    "clown nose": 3,
    "cowboy hat": 23,
    "crown": 4,
    "dark eyeshadow": 1,
    "devil horns": 1,
    "diver suit": 1,
    "earring": 15,
    "eyelash": 1,
    "eye mask": 4,
    "eye patch": 3,
    "face mask": 3,
    "face painting": 16,
    "fedora": 20,
    "frown": 70,
    "glass eye": 3,
    "goat": 2,
    "goatee": 28,
    "goggles": 4,
    "gold chain": 4,
    "green eyeshadow": 1,
    "hair clip": 3,
    "handlebars": 9,
    "headband": 9,
    "head scarf": 1,
    "headset mic": 2,
    "helmet": 10,
    "hoodie": 7,
    "horned rim glasses": 19,
    "knitted cap": 12,
    "lantern glasses": 1,
    "leaf hat": 1,
    "military cap": 1,
    "mohawk": 1,
    "mole": 12,
    "mustache": 51,
    "muttonchops": 11,
    "muzzle mask": 3,
    "necklace": 11,
    "nerd glasses": 4,
    "normal beard": 24,
    "normal shades": 2,
    "nose mask": 2,
    "nurse beret": 1,
    "oil": 1,
    "peaked cap": 8,
    "pink eyeshadow": 1,
    "pink lipstick": 2,
    "pipe": 5,
    "purple eyeshadow": 2,
    "red ball gag": 2,
    "red lipstick": 19,
    "robot eyes": 1,
    "robot face": 2,
    "robot mouth": 1,
    "round shades": 17,
    "royal hat": 1,
    "royal wig": 1,
    "santa beret": 2,
    "scar": 8,
    "shadow beard": 37,
    "smile": 1,
    "smirk": 57,
    "sombrero": 1,
    "soul patch": 9,
    "tattoo": 1,
    "tiny top hat": 1,
    "toothbrush mustache": 3,
    "top hat": 5,
    "trapper hat": 1,
    "waiter cap": 1
  },
  "background": {
    "17e6b7": 1,
    "419fc3": 54,
    "60a69b": 50,
    "844816": 1,
    "858384": 51,
    "990000": 1,
    "a24b42": 50,
    "a56ba0": 1,
    "d0a046": 1,
    "d0c6a3": 52,
    "e9be31": 52,
    "efc723": 1,
    "f2f2f2": 1,
    "fed21b": 1,
    "ffa401": 51
  },
  "movie": {
    "101 dalmatians": 1,
    "24 hour party people": 1,
    "300": 1,
    "8½": 1,
    "8 mile": 1,
    "ace ventura: pet detective": 1,
    "a clockwork orange": 1,
    "alice in wonderland": 2,
    "amadeus": 1,
    "amelie": 1,
    "american history x": 1,
    "american psycho": 1,
    "an american werewolf in london": 1,
    "anchorman: the legend of ron burgundy": 1,
    "apocalypse now": 1,
    "a series of unfortunate events": 1,
    "asterix & obelix vs caesar": 2,
    "a woman under the influence": 1,
    "back to the future": 2,
    "bad santa": 1,
    "barton fink": 1,
    "basic instinct": 1,
    "beetlejuice": 1,
    "beverly hills cop": 1,
    "big trouble in little china": 1,
    "black dynamite": 1,
    "black swan": 1,
    "blade": 1,
    "blade runner": 4,
    "blade runner 2049": 1,
    "bohemian rhapsody": 1,
    "boogie nights": 1,
    "braveheart": 1,
    "brazil": 1,
    "breakfast at tiffany's": 1,
    "bronson": 1,
    "bullitt": 1,
    "cape fear": 1,
    "carlito's way": 1,
    "carlos": 1,
    "casablanca": 1,
    "cast away": 1,
    "catch me if you can": 1,
    "charlie and the chocolate factory": 1,
    "chinatown": 1,
    "citizen kane": 1,
    "cleo from 5 to 7": 1,
    "clerks": 2,
    "coffee and cigarettes": 3,
    "collateral": 1,
    "control": 1,
    "crank": 1,
    "dallas buyers club": 1,
    "dances with wolves": 1,
    "dark shadows": 1,
    "dawn of the dead": 1,
    "day of the dead": 1,
    "dazed and confused": 1,
    "dead man": 1,
    "death proof": 1,
    "die hard": 2,
    "dirty harry": 1,
    "django: unchained": 4,
    "donnie darko": 1,
    "do the right thing": 1,
    "dracula": 2,
    "dr. strangelove or: how i learned to stop worrying and love the bomb": 1,
    "duck soup": 1,
    "easy rider": 2,
    "edward scissorhands": 1,
    "ed wood": 1,
    "enter the dragon": 1,
    "eraserhead": 1,
    "escape from new york": 1,
    "eternal sunshine of the spotless mind": 1,
    "falling down": 1,
    "fargo": 1,
    "fear and loathing in las vegas": 2,
    "fight club": 2,
    "first blood": 1,
    "frida": 1,
    "from dusk till dawn": 2,
    "gangs of new york": 1,
    "get carter": 1,
    "ghost dog: the way of the samurai": 1,
    "ghost world": 2,
    "gladiator": 2,
    "good will hunting": 1,
    "halloween": 1,
    "hancock": 1,
    "harry potter franchise": 4,
    "heat": 4,
    "hellboy": 1,
    "her": 1,
    "hot fuzz": 2,
    "how the grinch stole christmas": 1,
    "i'm not there": 1,
    "inglourious basterds": 2,
    "interview with the vampire": 3,
    "it": 1,
    "jackie brown": 3,
    "jaws": 2,
    "joker": 1,
    "jumanji": 1,
    "kill bill": 4,
    "killer joe": 1,
    "kingsman: the secret service": 2,
    "la haine": 1,
    "la strada": 1,
    "lenny": 1,
    "leon": 2,
    "lethal weapon": 2,
    "let the right one in": 1,
    "life of pi": 1,
    "logan": 1,
    "machete": 1,
    "mad max: fury road": 8,
    "malcolm x": 1,
    "man on fire": 1,
    "marie antoinette": 1,
    "memento": 1,
    "men in black": 2,
    "metropolis": 1,
    "miami vice": 2,
    "midnight cowboy": 1,
    "modern times": 1,
    "murder on the orient express": 1,
    "natural born killers": 2,
    "near dark": 1,
    "nightcrawler": 1,
    "no country for old men": 1,
    "nosferatu": 1,
    "nosferatu: the vampyre": 1,
    "oldboy": 1,
    "once upon a time in the west": 1,
    "one flew over the cuckoo's nest": 1,
    "patch adams": 1,
    "paths of glory": 1,
    "pirates of the caribbean franchise": 1,
    "planet terror": 1,
    "platoon": 2,
    "predator": 1,
    "psycho": 1,
    "public enemy no1": 1,
    "pulp fiction": 5,
    "raging bull": 1,
    "raiders of the lost ark": 1,
    "reservoir dogs": 6,
    "robocop": 1,
    "rocky": 1,
    "rushmore": 2,
    "safety last!": 1,
    "scarface": 1,
    "schindler's list": 1,
    "se7en": 2,
    "serpico": 1,
    "sexy beast": 1,
    "shaft": 1,
    "shaun of the dead": 2,
    "shutter island": 3,
    "sicario": 1,
    "sid & nancy": 1,
    "sin city": 8,
    "skyfall": 1,
    "smokey and the bandit": 1,
    "snatch": 2,
    "some like it hot": 3,
    "star wars franchise": 10,
    "straight time": 1,
    "sweeney todd: the demon barber of fleet street": 2,
    "tango & cash": 2,
    "taxi driver": 1,
    "terminator 2: judgment day": 3,
    "the assassination of jesse james by the coward robert ford": 1,
    "the big lebowski": 2,
    "the blues brothers": 2,
    "the cabinet of dr. caligari": 1,
    "the chronicles of riddick": 1,
    "the crow": 1,
    "the darjeeling limited": 3,
    "the deer hunter": 2,
    "the devil's rejects": 1,
    "the evil dead": 1,
    "the fifth element": 1,
    "the general": 1,
    "the gold rush": 1,
    "the good, the bad and the ugly": 3,
    "the grand budapest hotel": 7,
    "the great dictator": 1,
    "the hangover": 4,
    "the hateful eight": 8,
    "the hound of baskervilles": 1,
    "the italian job": 1,
    "the killing": 1,
    "the king of comedy": 1,
    "the life aquatic with steve zissou": 3,
    "the lighthouse": 2,
    "the long goodbye": 1,
    "the lost boys": 1,
    "the man who fell to earth": 1,
    "the mask": 1,
    "the mask of zorro": 1,
    "the matrix": 4,
    "the pink panther": 1,
    "the princess bride": 1,
    "there will be blood": 1,
    "the rocky horror picture show": 1,
    "the royal tenenbaums": 6,
    "the seventh seal": 2,
    "the shining": 1,
    "the silence of the lambs": 1,
    "the thing": 1,
    "the untouchables": 1,
    "the wizard of oz": 1,
    "the world's end": 2,
    "they live!": 2,
    "thief": 1,
    "top gun": 1,
    "training day": 1,
    "tropic thunder": 4,
    "troy": 2,
    "true grit": 1,
    "true romance": 1,
    "unbreakable": 1,
    "uncut gems": 2,
    "unforgiven": 1,
    "up in smoke": 2,
    "v for vendetta": 1,
    "war of the planet of the apes": 1,
    "watchmen": 3,
    "westworld": 1,
    "withnail & i": 2,
    "yojimbo": 1,
    "zombieland": 2
  },
  "type": {
    "alien": 1,
    "ape": 2,
    "devil": 1,
    "entity": 1,
    "female": 37,
    "ghost": 2,
    "male": 296,
    "mutant": 1,
    "robot": 9,
    "undead": 1,
    "vampire": 12,
    "werewolf": 1,
    "zombie": 4
  }
}