{
  "banner_image_url": "https://i.seadn.io/gcs/files/96a0c93b3d0be3ea8eb9fe21a8d763c9.png?w=500&auto=format",
  "chat_url": null,
  "created_date": "2022-07-17T13:50:09.222846+00:00",
  "default_to_fiat": false,
  "description": "Saudis may be bidding Bitcoin, but who is bidding Saudis? 🇮🇱 5555 Jews are MAX BIDDING THE WORLD",
  "discord_url": "https://discord.gg/thejews",
  "display_data": {
    "card_display_style": "contain"
  },
  "external_url": "https://thejewsnft.com/",
  "featured": false,
  "featured_image_url": "https://i.seadn.io/gcs/files/3cd9c2ca8cc2703fce3cd870e7d413f5.png?w=500&auto=format",
  "hidden": false,
  "safelist_request_status": "approved",
  "image_url": "https://i.seadn.io/gcs/files/de402a0bdf26c744ccaf272d4baeb318.png?w=500&auto=format",
  "is_subject_to_whitelist": false,
  "large_image_url": "https://i.seadn.io/gcs/files/3cd9c2ca8cc2703fce3cd870e7d413f5.png?w=500&auto=format",
  "medium_username": null,
  "name": "TheJewsNFT",
  "only_proxied_transfers": false,
  "require_email": false,
  "short_description": null,
  "slug": "thejews-nft",
  "telegram_url": null,
  "twitter_username": null,
  "instagram_username": null,
  "wiki_url": null,
  "is_nsfw": false,
  "fees": {
    "seller_fees": {
      "0x34e59c038a80e890b251b842b3742efbef53f54d": 1000
    },
    "opensea_fees": {
      "0x0000a26b00c1f0df003000390027140000faa719": 250
    }
  },
  "is_rarity_enabled": true
}